[
  {
    "id": "INV-001",
    "invoiceName": "Website Design",
    "invoiceDate": "2025-06-01",
    "paymentDate": "2025-06-10",
    "clientName": "Acme Corp",
    "clientEmail": "client@acme.com",
    "status": "Paid",
    "items": [
      {
        "itemName": "Landing Page Design",
        "quantity": "2",
        "price": "500",
        "total": "1000"
      },
      {
        "itemName": "Logo Design",
        "quantity": "1",
        "price": "200",
        "total": "200"
      }
    ],
    "clientCountry": "USA",
    "clientCity": "New York",
    "clientStreetName": "Broadway",
    "clientStreetNumber": "123"
  },
  {
    "id": "INV-002",
    "invoiceName": "Mobile App Development",
    "invoiceDate": "2025-05-25",
    "paymentDate": "2025-06-15",
    "clientName": "BetaTech",
    "clientEmail": "info@betatech.com",
    "status": "Pending",
    "items": [
      {
        "itemName": "iOS App",
        "quantity": "1",
        "price": "3000",
        "total": "3000"
      },
      {
        "itemName": "Android App",
        "quantity": "1",
        "price": "3000",
        "total": "3000"
      }
    ],
    "clientCountry": "Canada",
    "clientCity": "Toronto",
    "clientStreetName": "King Street",
    "clientStreetNumber": "456"
  },
  {
    "id": "INV-003",
    "invoiceName": "SEO Optimization",
    "invoiceDate": "2025-04-15",
    "paymentDate": "2025-04-30",
    "clientName": "Gamma LLC",
    "clientEmail": "contact@gammallc.com",
    "status": "Draft",
    "items": [
      {
        "itemName": "Initial Audit",
        "quantity": "1",
        "price": "400",
        "total": "400"
      },
      {
        "itemName": "Monthly Maintenance",
        "quantity": "3",
        "price": "250",
        "total": "750"
      }
    ],
    "clientCountry": "UK",
    "clientCity": "London",
    "clientStreetName": "Oxford Street",
    "clientStreetNumber": "789"
  }
]
